README.rst
setup.py
surefire/__init__.py
surefire.egg-info/PKG-INFO
surefire.egg-info/SOURCES.txt
surefire.egg-info/dependency_links.txt
surefire.egg-info/requires.txt
surefire.egg-info/top_level.txt
surefire.egg-info/zip-safe
surefire/features/__init__.py
surefire/modules/__init__.py
surefire/modules/combine.py
surefire/modules/feedforward.py