Metadata-Version: 1.0
Name: surefire
Version: 0.1.0
Summary: PyTorch models for structured data
Home-page: https://github.com/jasonkriss/surefire
Author: Jason Kriss
Author-email: jasonkriss@gmail.com
License: MIT
Platform: UNKNOWN
